fulfil_client/__init__.py
fulfil_client/client.py
fulfil_client/exceptions.py
fulfil_client/model.py
fulfil_client/oauth.py
fulfil_client/serialization.py
fulfil_client/signals.py
fulfil_client/contrib/__init__.py
fulfil_client/contrib/kombu.py
fulfil_client/contrib/mail.py
fulfil_client/contrib/mocking.py
fulfil_client-3.0.0.dist-info/licenses/AUTHORS.rst
fulfil_client-3.0.0.dist-info/licenses/LICENSE
fulfil_client-3.0.0.dist-info/METADATA
fulfil_client-3.0.0.dist-info/WHEEL
fulfil_client-3.0.0.dist-info/entry_points.txt
fulfil_client-3.0.0.dist-info/top_level.txt
fulfil_client-3.0.0.dist-info/RECORD
