Metadata-Version: 2.4
Name: fulfil_client
Version: 3.0.0
Summary: Fulfil REST API Client in Python
Home-page: https://github.com/fulfilio/fulfil-python-api
Author: Fulfil.IO Inc.
Author-email: hello@fulfil.io
License: ISCL
Keywords: fulfil_client
Classifier: Development Status :: 2 - Pre-Alpha
Classifier: Intended Audience :: Developers
Classifier: License :: OSI Approved :: ISC License (ISCL)
Classifier: Natural Language :: English
Classifier: Programming Language :: Python :: 2
Classifier: Programming Language :: Python :: 2.7
License-File: LICENSE
License-File: AUTHORS.rst
Requires-Dist: pyjwt
Requires-Dist: requests
Requires-Dist: requests_oauthlib
Requires-Dist: money
Requires-Dist: babel
Requires-Dist: six
Requires-Dist: more-itertools
Requires-Dist: isodate
Dynamic: author
Dynamic: author-email
Dynamic: classifier
Dynamic: description
Dynamic: home-page
Dynamic: keywords
Dynamic: license
Dynamic: license-file
Dynamic: requires-dist
Dynamic: summary
